django_issue_capture/__init__.py
django_issue_capture/admin.py
django_issue_capture/apps.py
django_issue_capture/context_processors.py
django_issue_capture/llm_service.py
django_issue_capture/models.py
django_issue_capture/services.py
django_issue_capture/urls.py
django_issue_capture/views.py
django_issue_capture/management/__init__.py
django_issue_capture/management/commands/__init__.py
django_issue_capture/management/commands/setup_issue_templates.py
django_issue_capture/migrations/0001_initial.py
django_issue_capture/migrations/0002_remove_chat_feature.py
django_issue_capture/migrations/0003_alter_issuecapturesettings_llm_model_and_more.py
django_issue_capture/migrations/0004_remove_issuecapturesettings_llm_enabled_and_more.py
django_issue_capture/migrations/0005_issuecapturesettings_staff_only.py
django_issue_capture/migrations/__init__.py
django_issue_capture/templates/base.html
django_issue_capture/templates/django_issue_capture/_create_form.html
django_issue_capture/templates/django_issue_capture/_generation_error.html
django_issue_capture/templates/django_issue_capture/_issue_button.html
django_issue_capture/templates/django_issue_capture/_issue_preview.html
django_issue_capture/templates/django_issue_capture/_success_notification.html
django_issue_capture/templates/django_issue_capture/admin_row_update.html
django_issue_capture/templates/django_issue_capture/detail.html
django_issue_capture/templates/django_issue_capture/dual_mode_interface.html
django_issue_capture/templates/django_issue_capture/list.html
django_issue_capture-0.2.2.dist-info/METADATA
django_issue_capture-0.2.2.dist-info/WHEEL
django_issue_capture-0.2.2.dist-info/licenses/LICENSE
django_issue_capture-0.2.2.dist-info/RECORD
