Metadata-Version: 2.4
Name: django-issue-capture
Version: 0.2.2
Summary: AI-powered GitHub issue creation and management system for Django with conversational UX and LLM enhancement
Project-URL: Homepage, https://github.com/directory-platform/django-issue-capture
Project-URL: Repository, https://github.com/directory-platform/django-issue-capture
Project-URL: Issues, https://github.com/directory-platform/django-issue-capture/issues
Author: Directory Platform Team
License: MIT
License-File: LICENSE
Keywords: ai,django,github,issue-tracking,issues,litellm,llm
Classifier: Development Status :: 4 - Beta
Classifier: Environment :: Web Environment
Classifier: Framework :: Django
Classifier: Framework :: Django :: 4.2
Classifier: Framework :: Django :: 5.0
Classifier: Framework :: Django :: 5.1
Classifier: Intended Audience :: Developers
Classifier: License :: OSI Approved :: MIT License
Classifier: Operating System :: OS Independent
Classifier: Programming Language :: Python
Classifier: Programming Language :: Python :: 3
Classifier: Programming Language :: Python :: 3.12
Classifier: Topic :: Internet :: WWW/HTTP
Classifier: Topic :: Internet :: WWW/HTTP :: Dynamic Content
Classifier: Topic :: Software Development :: Bug Tracking
Classifier: Topic :: Software Development :: Libraries :: Python Modules
Classifier: Typing :: Typed
Requires-Python: >=3.12
Requires-Dist: django-markdownify>=0.9
Requires-Dist: django-solo>=2.0
Requires-Dist: django>=4.2
Requires-Dist: litellm>=1.70
Requires-Dist: requests>=2.32
Requires-Dist: shortuuid>=1.0
Provides-Extra: dev
Requires-Dist: django-stubs>=4.2.0; extra == 'dev'
Requires-Dist: mypy>=1.7.0; extra == 'dev'
Requires-Dist: ruff>=0.1.0; extra == 'dev'
